{
  "pill_00003_4222_16": {
    "precision": 1.0,
    "recall": 1.0,
    "f1-score": 1.0,
    "support": 1.0
  },
  "pill_00004_0800_85": {
    "precision": 1.0,
    "recall": 1.0,
    "f1-score": 1.0,
    "support": 1.0
  },
  "pill_00006_0277_54": {
    "precision": 1.0,
    "recall": 1.0,
    "f1-score": 1.0,
    "support": 1.0
  },
  "pill_00023_9350_07": {
    "precision": 1.0,
    "recall": 1.0,
    "f1-score": 1.0,
    "support": 1.0
  },
  "pill_00029_3159_13": {
    "precision": 1.0,
    "recall": 1.0,
    "f1-score": 1.0,
    "support": 1.0
  },
  "accuracy": 1.0,
  "macro avg": {
    "precision": 1.0,
    "recall": 1.0,
    "f1-score": 1.0,
    "support": 5.0
  },
  "weighted avg": {
    "precision": 1.0,
    "recall": 1.0,
    "f1-score": 1.0,
    "support": 5.0
  }
}